<Properties StartupConfiguration="{19512EA1-574A-4C6C-95F1-2AAC6B3B5460}|Default">
  <MonoDevelop.Ide.Workbench ActiveDocument="Controllers/HomeController.cs">
    <Files>
      <File FileName="Controllers/HomeController.cs" Line="35" Column="4" />
    </Files>
  </MonoDevelop.Ide.Workbench>
  <MonoDevelop.Ide.Workspace ActiveConfiguration="Debug" />
  <MonoDevelop.Ide.DebuggingService.Breakpoints>
    <BreakpointStore />
  </MonoDevelop.Ide.DebuggingService.Breakpoints>
  <MonoDevelop.Ide.DebuggingService.PinnedWatches />
  <MonoDevelop.Ide.ItemProperties.TaskRouterDotNetCore PreferredExecutionTarget="MonoDevelop.Default" />
  <MultiItemStartupConfigurations />
</Properties>